deitheon/__init__.py
deitheon-0.1.1.dist-info/METADATA
deitheon-0.1.1.dist-info/WHEEL
deitheon-0.1.1.dist-info/top_level.txt
deitheon-0.1.1.dist-info/RECORD
