Metadata-Version: 2.1
Name: deitheon
Version: 0.1.1
Summary: deitheon Package
Home-page: https://github.com/yourusername/deitheon
Author: Your Name
Author-email: your.email@example.com
License: UNKNOWN
Platform: UNKNOWN
Classifier: Programming Language :: Python :: 3
Classifier: License :: OSI Approved :: MIT License
Classifier: Operating System :: OS Independent
Requires-Python: >=3.6
Requires-Dist: datasalgo
Requires-Dist: matplotlib
Requires-Dist: numpy
Requires-Dist: pandas
Requires-Dist: tensorflow
Requires-Dist: torch
Requires-Dist: transformers
Requires-Dist: utilum
